httphelp/__init__.py
httphelp/__main__.py
httphelp/app_handler.py
httphelp/code_descriptions.yml
httphelp/constants.py
httphelp/content_generator.py
httphelp/copyright_description.yml
httphelp/header_descriptions.yml
httphelp/statcode.py
httphelp-1.1.1.post1.dist-info/LICENSE
httphelp-1.1.1.post1.dist-info/METADATA
httphelp-1.1.1.post1.dist-info/WHEEL
httphelp-1.1.1.post1.dist-info/entry_points.txt
httphelp-1.1.1.post1.dist-info/top_level.txt
httphelp-1.1.1.post1.dist-info/RECORD
