Metadata-Version: 2.1
Name: httphelp
Version: 1.1.1.post1
Summary: Like man pages, but for HTTP status codes and headers (and more)
Home-page: https://github.com/Malex/statcode
Author: Malex
Author-email: malexprojects@gmail.com
License: MIT
Platform: UNKNOWN
Requires-Python: >=3
Requires-Dist: pyyaml
Requires-Dist: urwid
